twottle/__init__.py
twottle/app.py
twottle/config.ini
twottle/static/style.css
twottle/views/base.html
twottle/views/channel.html
twottle/views/error.html
twottle/views/following.html
twottle/views/games.html
twottle/views/index.html
twottle/views/login.html
twottle/views/search.html
twottle/views/settings.html
twottle/views/streams.html
twottle/views/watching.html
twottle-0.7.7.dist-info/entry_points.txt
twottle-0.7.7.dist-info/LICENSE
twottle-0.7.7.dist-info/WHEEL
twottle-0.7.7.dist-info/METADATA
twottle-0.7.7.dist-info/RECORD
