Metadata-Version: 2.1
Name: twottle
Version: 0.7.7
Summary: Web GUI for streamlink cli
Author-email: Raeed Ahmed <ruahmed7868@gmail.com>
Classifier: License :: OSI Approved :: GNU General Public License v3 or later (GPLv3+)
Requires-Dist: bottle
Requires-Dist: httpx
Requires-Dist: peewee
Requires-Dist: waitress
Requires-Dist: streamlink
Requires-Dist: yt-dlp
Project-URL: Home, https://github.com/RaeedAhmed/twottle
